copier_example/__init__.py
copier_example/__main__.py
copier_example/_version.py
copier_example-0.15.dist-info/LICENSE
copier_example-0.15.dist-info/METADATA
copier_example-0.15.dist-info/WHEEL
copier_example-0.15.dist-info/entry_points.txt
copier_example-0.15.dist-info/top_level.txt
copier_example-0.15.dist-info/RECORD
